sphinxcontrib_erlangdomain-0.2.1-py3.10-nspkg.pth
sphinxcontrib/erlangdomain.py
sphinxcontrib_erlangdomain-0.2.1.dist-info/LICENSE
sphinxcontrib_erlangdomain-0.2.1.dist-info/METADATA
sphinxcontrib_erlangdomain-0.2.1.dist-info/WHEEL
sphinxcontrib_erlangdomain-0.2.1.dist-info/namespace_packages.txt
sphinxcontrib_erlangdomain-0.2.1.dist-info/top_level.txt
sphinxcontrib_erlangdomain-0.2.1.dist-info/RECORD
