Metadata-Version: 2.1
Name: sphinxcontrib-erlangdomain
Version: 0.2.1
Summary: Sphinx extension sphinxcontrib-erlangdomain
Home-page: https://github.com/hio/sphinx-erlangdomain
Author: SHIBUKAWA Yoshiki
Author-email: yoshiki@shibu.jp
Maintainer: YAMASHINA Hio
Maintainer-email: hio@hio.jp
License: BSD
Download-URL: https://pypi.org/project/sphinxcontrib-erlangdomain/
Project-URL: Documentation, https://sphinxcontrib-erlangdomain.readthedocs.io/en/latest/
Project-URL: Source, https://github.com/hio/sphinx-erlangdomain
Platform: any
Classifier: Development Status :: 4 - Beta
Classifier: Environment :: Console
Classifier: Environment :: Web Environment
Classifier: Intended Audience :: Developers
Classifier: License :: OSI Approved :: BSD License
Classifier: Operating System :: OS Independent
Classifier: Programming Language :: Python
Classifier: Programming Language :: Erlang
Classifier: Topic :: Documentation
Classifier: Topic :: Utilities
License-File: LICENSE
Requires-Dist: Sphinx (>=1.0)
